milspend.py
milspend-0.0.5.dist-info/METADATA
milspend-0.0.5.dist-info/WHEEL
milspend-0.0.5.dist-info/entry_points.txt
milspend-0.0.5.dist-info/top_level.txt
milspend-0.0.5.dist-info/RECORD
