Metadata-Version: 2.1
Name: milspend
Version: 0.0.5
Summary: A package for visualizing military spending of up to 4 countries
Home-page: https://github.com/y-takefuji/defense
Author: yoshiyasu takefuji
Author-email: takefuji@keio.jp
License: UNKNOWN
Project-URL: Bug Tracker, https://github.com/y-takefuji/defense
Platform: UNKNOWN
Classifier: Programming Language :: Python :: 3
Classifier: License :: OSI Approved :: MIT License
Classifier: Operating System :: OS Independent
Requires-Python: >=3.8
